pyPeruStats/__init__.py
pyPeruStats/BCRP/__init__.py
pyPeruStats/BCRP/fetcher.py
pyPeruStats/INEI/__init__.py
pyPeruStats/INEI/old.py
pyPeruStats/INEI/process/__init__.py
pyPeruStats/INEI/process/microdatos.py
pyPeruStats/INEI/utils.py
pyPeruStats/utils.py
pyperustats-0.1.2.dist-info/LICENSE
pyperustats-0.1.2.dist-info/METADATA
pyperustats-0.1.2.dist-info/WHEEL
pyperustats-0.1.2.dist-info/RECORD
