Metadata-Version: 2.1
Name: pyperustats
Version: 0.1.2
Summary: Allows downloading data from various data sources in Peru.
Home-page: https://github.com/TJhon/PyPeruStats
License: Apache-2.0
Author: Jhon K. Flores Rojas
Author-email: fr.jhonk@gmail.com
Requires-Python: >=3.10,<4.0
Classifier: License :: OSI Approved :: Apache Software License
Classifier: Programming Language :: Python :: 3
Classifier: Programming Language :: Python :: 3.10
Classifier: Programming Language :: Python :: 3.11
Classifier: Programming Language :: Python :: 3.12
Classifier: Programming Language :: Python :: 3.13
Requires-Dist: bs4 (>=0.0.2,<0.0.3)
Requires-Dist: fastparquet (>=2024.11.0,<2025.0.0)
Requires-Dist: ipykernel (>=6.29.5,<7.0.0)
Requires-Dist: lxml (>=5.3.0,<6.0.0)
Requires-Dist: numpy (>=2.2.0,<3.0.0)
Requires-Dist: pandas (>=2.2.3,<3.0.0)
Requires-Dist: pyarrow (>=18.1.0,<19.0.0)
Requires-Dist: requests (>=2.32.3,<3.0.0)
Requires-Dist: termcolor (>=2.5.0,<3.0.0)
Requires-Dist: tqdm (>=4.67.1,<5.0.0)
Requires-Dist: unidecode (>=1.3.8,<2.0.0)
